networkx_astar_path/__init__.py
networkx_astar_path/astar.py
networkx_astar_path/py.typed
networkx_astar_path-1.0.1.dist-info/LICENSE
networkx_astar_path-1.0.1.dist-info/WHEEL
networkx_astar_path-1.0.1.dist-info/METADATA
networkx_astar_path-1.0.1.dist-info/RECORD
