Metadata-Version: 2.1
Name: networkx-astar-path
Version: 1.0.1
Summary: Alternative A* implementation, which provides the current and previous edge to the weight function.
Home-page: https://github.com/escaped/networkx-astar-path
License: BSD-3-Clause
Author: Alexander Frenzel
Author-email: alex@relatedworks.com
Requires-Python: >=3.6.1,<4.0
Classifier: Development Status :: 4 - Beta
Classifier: Environment :: Web Environment
Classifier: Intended Audience :: Developers
Classifier: License :: OSI Approved :: BSD License
Classifier: Operating System :: OS Independent
Classifier: Programming Language :: Python
Classifier: Programming Language :: Python :: 3
Classifier: Programming Language :: Python :: 3.6
Classifier: Programming Language :: Python :: 3.7
Classifier: Programming Language :: Python :: 3.8
Classifier: Programming Language :: Python :: 3.9
Classifier: Topic :: Software Development :: Libraries :: Python Modules
Classifier: Typing :: Typed
Requires-Dist: networkx (>=2.5)
Project-URL: Documentation, https://github.com/escaped/networkx-astar-path/blob/master/README.md
Project-URL: Repository, https://github.com/escaped/networkx-astar-path
